asl/__init__.py
asl/pipeline.py
asl/data/__init__.py
asl/data/dataset.py
asl/data/preprocessor.py
asl/detection/__init__.py
asl/detection/hand_detector.py
asl/models/__init__.py
asl/models/coords_model.py
asl/models/model_factory.py
asl/utils/__init__.py
asl/utils/config.py
asl/visualization/__init__.py
asl/visualization/visualizer.py
asl_detection-0.1.1.dist-info/METADATA
asl_detection-0.1.1.dist-info/WHEEL
asl_detection-0.1.1.dist-info/top_level.txt
asl_detection-0.1.1.dist-info/RECORD
