Metadata-Version: 2.4
Name: asl-detection
Version: 0.1.1
Summary: ASL detection using computer vision and deep learning
Home-page: https://github.com/ce20480/SignLanguageDetection
Author: Avini
Author-email: avinibusiness@gmail.com
Classifier: Programming Language :: Python :: 3
Classifier: License :: OSI Approved :: MIT License
Classifier: Operating System :: OS Independent
Requires-Python: >=3.9, <=3.12
Requires-Dist: numpy>=1.19.0
Requires-Dist: opencv-python>=4.5.0
Requires-Dist: torch>=1.9.0
Requires-Dist: matplotlib>=3.3.0
Requires-Dist: scikit-learn>=0.24.0
Requires-Dist: mediapipe>=0.10.18
Dynamic: author
Dynamic: author-email
Dynamic: classifier
Dynamic: description
Dynamic: description-content-type
Dynamic: home-page
Dynamic: requires-dist
Dynamic: requires-python
Dynamic: summary
